polars_kde-0.1.4.dist-info/METADATA
polars_kde-0.1.4.dist-info/WHEEL
polars_kde-0.1.4.dist-info/licenses/LICENSE
polars_kde/__init__.py
polars_kde/typing.py
polars_kde/polars_kde.abi3.so
polars_kde-0.1.4.dist-info/RECORD
