Metadata-Version: 2.4
Name: polars_kde
Version: 0.1.4
License-File: LICENSE
Summary: Add your description here
Requires-Python: >=3.12
